{"numFrames":1,"task":"","start_time":0,"end_time":0,"total_time":0,"sessionNumber":8,"tickRate":6.0,"frames":[{"frameNum":1205,"unixTime":1652744067566,"timestamp":121712,"hPos":{"x":-0.15969252586364747,"y":0.0018970590317621828,"z":0.13817819952964784},"hDir":{"x":-0.21590648591518403,"y":-0.11225417256355286,"z":0.9699398875236511},"hRot":{"x":0.05540793389081955,"y":-0.10936185717582703,"z":0.010425537824630738,"w":0.9924017786979675},"hAngl":{"x":6.44527530670166,"y":347.45068359375,"z":0.4943626821041107},"gazeOrigin":{"x":-0.15738484263420106,"y":0.0022373259998857977,"z":0.1427813172340393},"gazeDirection":{"x":-0.22052422165870667,"y":-0.11272569745779038,"z":0.9688457250595093},"rightHandRay":{"x":-0.2456827163696289,"y":-0.1856202781200409,"z":0.79638671875},"leftHandRay":{"x":0.0,"y":0.0,"z":0.0},"experimentEvents":[{"unixTime":1652744067546,"systemTime":"16-34-27-54","isResponsive":false,"eventName":"entered","task_number":8,"task_type":"Scroll","object_scale":{"x":1.0,"y":1.0,"z":1.0},"object_position":{"x":0.0,"y":0.0,"z":0.75},"correct_answer":"8","guess":"8"},{"unixTime":1652744067546,"systemTime":"16-34-27-54","isResponsive":false,"eventName":"end","task_number":8,"task_type":"Scroll","object_scale":{"x":1.0,"y":1.0,"z":1.0},"object_position":{"x":0.0,"y":0.0,"z":0.75},"correct_answer":"8","guess":"8"}],"responsiveData":{"scale":{"x":0.0,"y":0.0,"z":0.0},"position":{"x":0.0,"y":0.0,"z":0.0},"ratio":0.0,"distance":0.0}}],"isResponsive":false}